{
  "nid" : 252741,
  "name" : "Rich Funke",
  "lastName" : "Funke",
  "shortName" : "Funke",
  "email" : "Funke@nysenate.gov",
  "additionalContact" : "",
  "imageUrl" : "http://www.nysenate.gov/files/profile-pictures/Funke_Unofficial_Headshot.jpg",
  "url" : "http://www.nysenate.gov/senator/rich-funke",
  "partyAffiliations" : [ "R" ],
  "offices" : [ {
    "name" : "Albany Office",
    "street" : "Legislative Office Building,",
    "city" : "Albany",
    "postalCode" : "12247",
    "provinceName" : "New York",
    "province" : "NY",
    "countryName" : "United States",
    "country" : "us",
    "phone" : "(518) 455-",
    "fax" : "(518) 426-",
    "otherPhone" : "",
    "additional" : "Room 302",
    "latitude" : 42.65,
    "longitude" : -73.76
  } ],
  "district" : {
    "number" : 55,
    "url" : "http://www.nysenate.gov/district/55",
    "imageUrl" : "http://www.nysenate.gov/files/district_55.png",
    "mapUrl" : "http://geo.nysenate.gov/maps/regular.jsp?x=850&y=595&sd=55"
  },
  "social" : {
    "twitter" : "",
    "youtube" : "",
    "myspace" : "",
    "picasa" : "",
    "flickr" : "",
    "facebook" : ""
  }
}