{
  "nid" : 172641,
  "name" : "Cecilia Tkaczyk",
  "lastName" : "Tkaczyk",
  "shortName" : "Tkaczyk",
  "email" : "tkaczyk@nysenate.gov",
  "additionalContact" : "",
  "imageUrl" : "http://www.nysenate.gov/files/profile-pictures/(12-10-12) Tkaczyk-HS-009.jpg",
  "url" : "http://www.nysenate.gov/senator/cecilia-tkaczyk",
  "partyAffiliations" : [ "D" ],
  "offices" : [ {
    "name" : "Albany Office",
    "street" : "311 Legislative Office Building",
    "city" : "Albany",
    "postalCode" : "12247",
    "provinceName" : "New York",
    "province" : "NY",
    "countryName" : "United States",
    "country" : "us",
    "phone" : "518-455-2470",
    "fax" : "",
    "otherPhone" : "",
    "additional" : "Empire State Plaza",
    "latitude" : 42.652442,
    "longitude" : -73.759332
  }, {
    "name" : "District Office",
    "street" : "42 Crown St,",
    "city" : "Kingston",
    "postalCode" : "12401",
    "provinceName" : "New York",
    "province" : "NY",
    "countryName" : "United States",
    "country" : "us",
    "phone" : "845-331-3810",
    "fax" : "",
    "otherPhone" : "",
    "additional" : "",
    "latitude" : 41.933911,
    "longitude" : -74.020752
  }, {
    "name" : "Satellite Office",
    "street" : "1170 Riverfront Center",
    "city" : "Amsterdam",
    "postalCode" : "12010",
    "provinceName" : "New York",
    "province" : "NY",
    "countryName" : "United States",
    "country" : "us",
    "phone" : "518-842-2407",
    "fax" : "",
    "otherPhone" : "",
    "additional" : "1st Floor",
    "latitude" : 42.936699,
    "longitude" : -74.189727
  } ],
  "district" : {
    "number" : 46,
    "url" : "http://www.nysenate.gov/district/46",
    "imageUrl" : "http://www.nysenate.gov/files/district_46.png",
    "mapUrl" : "http://geo.nysenate.gov/maps/regular.jsp?x=850&y=595&sd=46"
  },
  "social" : {
    "twitter" : "http://twitter.com/SenTkaczyk",
    "youtube" : "http://www.youtube.com/channel/UCAyHOgVndqCQUZf5ExeVPKg",
    "myspace" : "",
    "picasa" : "",
    "flickr" : "",
    "facebook" : "http://www.facebook.com/pages/Senator-Cecilia-Tkaczyk/296566983798700"
  }
}