{
  "nid" : 75011,
  "name" : "Mark Grisanti",
  "lastName" : "Grisanti",
  "shortName" : "Grisanti",
  "email" : "grisanti@nysenate.gov",
  "additionalContact" : "",
  "imageUrl" : "http://www.nysenate.gov/files/profile-pictures/Grisanti.jpg",
  "url" : "http://www.nysenate.gov/senator/mark-grisanti",
  "partyAffiliations" : [ "R", "IP" ],
  "offices" : [ {
    "name" : "Albany Office",
    "street" : "Room 902 Legislative Office Building",
    "city" : "Albany",
    "postalCode" : "12247",
    "provinceName" : "New York",
    "province" : "NY",
    "countryName" : "United States",
    "country" : "us",
    "phone" : "518-455-3240",
    "fax" : "518-426-6738",
    "otherPhone" : "",
    "additional" : "",
    "latitude" : 42.652442,
    "longitude" : -73.759332
  }, {
    "name" : "Buffalo Office",
    "street" : "65 Court Street",
    "city" : "Buffalo",
    "postalCode" : "14202",
    "provinceName" : "New York",
    "province" : "NY",
    "countryName" : "United States",
    "country" : "us",
    "phone" : "716-854-8705",
    "fax" : "716-854-3051",
    "otherPhone" : "",
    "additional" : "Room 213",
    "latitude" : 42.886548,
    "longitude" : -78.876876
  }, {
    "name" : "",
    "street" : "",
    "city" : "",
    "postalCode" : "",
    "provinceName" : "",
    "province" : "",
    "countryName" : "United States",
    "country" : "us",
    "phone" : "",
    "fax" : "",
    "otherPhone" : "",
    "additional" : "",
    "latitude" : 0.0,
    "longitude" : 0.0
  }, {
    "name" : "",
    "street" : "",
    "city" : "",
    "postalCode" : "",
    "provinceName" : "",
    "province" : "",
    "countryName" : "United States",
    "country" : "us",
    "phone" : "",
    "fax" : "",
    "otherPhone" : "",
    "additional" : "",
    "latitude" : 0.0,
    "longitude" : 0.0
  } ],
  "district" : {
    "number" : 60,
    "url" : "http://www.nysenate.gov/district/60",
    "imageUrl" : "http://www.nysenate.gov/files/district_60.png",
    "mapUrl" : "http://geo.nysenate.gov/maps/regular.jsp?x=850&y=595&sd=60"
  },
  "social" : {
    "twitter" : "http://twitter.com/senatorgrisanti",
    "youtube" : "http://www.youtube.com/results?search_query=senator+mark+grisanti&aq=f",
    "myspace" : "",
    "picasa" : "",
    "flickr" : "",
    "facebook" : "https://www.facebook.com/SenatorGrisanti"
  }
}