{"district":"State Senate District 8","districtUrl":"http://www.nysenate.gov/district/08","senator":{"name":"Charles J. Fuschillo Jr.","contact":"fuschill@senate.state.ny.us","url":"http://www.nysenate.gov/senator/charles-j-fuschillo-jr","imageUrl":"http://www.nysenate.gov/files/imagecache/senator_teaser/profile-pictures/Senator Fuschillo's Headshot-2011_0.JPG","social":{"contact":"fuschill@senate.state.ny.us","faceBook":"","twitter":"","youtube":"","flickr":"","rss":"http://www.nysenate.gov/senator/charles-j-fuschillo-jr/content/feed"},"offices":[{"street":"188 State Street ","city":"Albany","state":"NY","zip":"","lat":-73.759091,"lon":42.652855,"officeName":"Albany Office","phone":"518-455-3341","fax":"","id":33,"contact":"fuschill@senate.state.ny.us"},{"street":"5550 Merrick Road","city":"Massapequa","state":"NY","zip":"","lat":-73.432602,"lon":40.668929,"officeName":"District Office","phone":"516-882-0630","fax":"516-882-0636","id":34,"contact":"fuschill@senate.state.ny.us"}],"district":"State Senate District 8"}}