{
  "name" : "New York City Education Subcommittee",
  "shortName" : "educationsubcommittee",
  "url" : "http://www.nysenate.gov/committee/new-york-city-education-subcommittee",
  "videoUrl" : "http://www.livestream.com/NYSenate_NYC_Education",
  "chairs" : [ {
    "name" : "Simcha Felder",
    "shortName" : "felder",
    "url" : "http://www.nysenate.gov/senator/simcha-felder"
  } ],
  "members" : [ {
    "name" : "Andrew J Lanza",
    "shortName" : "lanza",
    "url" : "http://www.nysenate.gov/senator/andrew-j-lanza"
  }, {
    "name" : "Martin J. Golden",
    "shortName" : "golden",
    "url" : "http://www.nysenate.gov/senator/martin-j-golden"
  }, {
    "name" : "Simcha Felder",
    "shortName" : "felder",
    "url" : "http://www.nysenate.gov/senator/simcha-felder"
  }, {
    "name" : "Bill Perkins",
    "shortName" : "perkins",
    "url" : "http://www.nysenate.gov/senator/bill-perkins"
  }, {
    "name" : "Toby Ann Stavisky",
    "shortName" : "stavisky",
    "url" : "http://www.nysenate.gov/senator/toby-ann-stavisky"
  }, {
    "name" : "Diane J. Savino",
    "shortName" : "savino",
    "url" : "http://www.nysenate.gov/senator/diane-j-savino"
  } ]
}